lynse/__init__.py
lynse/api/__init__.py
lynse/api/http_api/__init__.py
lynse/api/http_api/client_api.py
lynse/api/http_api/http_api/__init__.py
lynse/api/http_api/http_api/app.py
lynse/api/http_api/http_api/collection_ops.py
lynse/api/http_api/http_api/database_ops.py
lynse/api/native_api/__init__.py
lynse/api/native_api/database_manager.py
lynse/api/native_api/high_level.py
lynse/api/native_api/low_level.py
lynse/computational_layer/__init__.py
lynse/computational_layer/engines.py
lynse/configs/__init__.py
lynse/configs/config.py
lynse/configs/parameters_validator.py
lynse/core_components/__init__.py
lynse/core_components/fast_sort.py
lynse/core_components/id_checker.py
lynse/core_components/ivf_index.py
lynse/core_components/kmeans.py
lynse/core_components/limited_dict.py
lynse/core_components/limited_sort.py
lynse/core_components/locks.py
lynse/core_components/safe_dict.py
lynse/core_components/fields_cache/__init__.py
lynse/core_components/fields_cache/expression_parse.py
lynse/core_components/fields_cache/fields_query.py
lynse/core_components/fields_cache/fields_storage.py
lynse/core_components/fields_cache/filter.py
lynse/core_components/fields_cache/index.py
lynse/execution_layer/__init__.py
lynse/execution_layer/indexer.py
lynse/execution_layer/ivf.py
lynse/execution_layer/matrix_serializer.py
lynse/execution_layer/search.py
lynse/execution_layer/session.py
lynse/index/__init__.py
lynse/index/base.py
lynse/index/binary.py
lynse/index/flat.py
lynse/index/sq.py
lynse/storage_layer/__init__.py
lynse/storage_layer/storage.py
lynse/storage_layer/wal.py
lynse/utils/__init__.py
lynse/utils/poster.py
lynse/utils/utils.py
test/__init__.py
test/docker_tests/__init__.py
test/docker_tests/test_client_api.py
test/docker_tests/test_docker_api.py
test/standard_tests/__init__.py
test/standard_tests/test_hl_initial.py
test/standard_tests/test_ll_initial.py
test/standard_tests/test_ll_save_and_query.py
test/standard_tests/test_multi_threads.py
LynseDB-0.1.6.dist-info/LICENSE
LynseDB-0.1.6.dist-info/METADATA
LynseDB-0.1.6.dist-info/WHEEL
LynseDB-0.1.6.dist-info/entry_points.txt
LynseDB-0.1.6.dist-info/top_level.txt
LynseDB-0.1.6.dist-info/RECORD
