Metadata-Version: 2.1
Name: LynseDB
Version: 0.1.6
Summary: A pure Python-implemented, lightweight, server-optional, multi-end compatible, vector database deployable locally or remotely.
Home-page: https://github.com/BirchKwok/MinVectorDB
Author: Birch Kwok
Author-email: birchkwok@gmail.com
Keywords: vector database
Classifier: Intended Audience :: Science/Research
Classifier: Intended Audience :: Developers
Classifier: Topic :: Software Development
Classifier: Topic :: Scientific/Engineering
Classifier: License :: OSI Approved :: Apache Software License
Classifier: Operating System :: OS Independent
Classifier: Programming Language :: Python :: 3.9
Classifier: Programming Language :: Python :: 3.10
Classifier: Programming Language :: Python :: 3.11
Classifier: Programming Language :: Python :: 3.12
Requires-Python: >=3.9
License-File: LICENSE
Requires-Dist: numpy>=1.17.0
Requires-Dist: spinesUtils>=0.4.1
Requires-Dist: msgpack>=1.0.2
Requires-Dist: scikit-learn>=1.0.0
Requires-Dist: cloudpickle>=2.0.0
Requires-Dist: pyroaring>=0.4.5
Requires-Dist: flask>=2.0.1
Requires-Dist: waitress>=2.0.0
Requires-Dist: tqdm>=4.65.0
Requires-Dist: setuptools>=68.0.0
Requires-Dist: httpx[socks]>=0.19.0
Requires-Dist: ruamel.yaml>=0.18.6
Requires-Dist: simsimd>=4.4.0
Requires-Dist: usearch>=2.12.0
